pyodbc_sqlite_orm_fmj/__init__.py
pyodbc_sqlite_orm_fmj/pyodbc_sqlite_orm_fmj.py
pyodbc_sqlite_orm_fmj-1.0.6.dist-info/LICENSE
pyodbc_sqlite_orm_fmj-1.0.6.dist-info/METADATA
pyodbc_sqlite_orm_fmj-1.0.6.dist-info/WHEEL
pyodbc_sqlite_orm_fmj-1.0.6.dist-info/top_level.txt
pyodbc_sqlite_orm_fmj-1.0.6.dist-info/RECORD
